{"speaker":{"id":2454,"title":"","firstname":"Fei-Fei","middleinitial":"","lastname":"Li","description":"Computer scientist","whotheyare":"As Director of Stanford\u2019s Artificial Intelligence Lab and Vision Lab, Fei-Fei Li is working to solve AI\u2019s trickiest problems -- including image recognition, learning and language processing.","whylisten":"<p>Using algorithms built on machine learning methods such as neural network models, the Stanford Artificial Intelligence Lab led by Fei-Fei Li has created software capable of recognizing scenes in still photographs -- and accurately describe them using natural language.<br \/><br \/>Li&rsquo;s work with neural networks and computer vision (with Stanford&rsquo;s Vision Lab) marks a significant step forward for AI research, and could lead to applications ranging from more intuitive image searches to robots able to make autonomous decisions in unfamiliar situations.<\/p><p>Fei-Fei was honored as one of <em>Foreign Policy<\/em>&#39;s 2015<a href=\"http:\/\/2015globalthinkers.foreignpolicy.com\/?utm_source=Sailthru&amp;utm_medium=email&amp;utm_campaign=New%20Campaign&amp;utm_term=Flashpoints#!challengers\/detail\/li-russakovsky-summers-ghadiyali-robyn\" target=\"_blank\">&nbsp;Global Thinkers<\/a>.&nbsp;<\/p>","slug":"fei_fei_li","published_at":"2015-01-31 15:03:00","updated_at":"2015-12-03 17:45:54"}}