{"speaker":{"id":3386,"title":"","firstname":"Marc","middleinitial":"","lastname":"Raibert","description":"Roboticist","whotheyare":"Marc Raibert is the founder and CEO of robot maker Boston Dynamics.","whylisten":"<p>Working with his team at Boston Dynamics, Marc Raibert builds some of the world&#39;s most advanced robots, such as BigDog, Atlas, Spot and Handle. These robots are inspired by the remarkable ability of animals to move with agility, dexterity, perception and intelligence. A key ingredient of these robots is their dynamic behavior, which contributes to their lifelike qualities and their effectiveness in the real world.&nbsp;<\/p><p>Raibert founded Boston Dynamics as a spinoff from MIT, where he ran the Leg Laboratory, which helped establish the scientific basis for highly dynamic robots. He was a professor of EE&amp;CS at MIT and before that associate professor of CS &amp; Robotics at Carnegie Mellon University.&nbsp;Raibert is a member of the National Academy of Engineering.<\/p>","slug":"marc_raibert","published_at":"2017-03-09 03:31:00","updated_at":"2017-07-31 14:47:22"}}