{"speaker":{"id":3455,"title":"","firstname":"Kate","middleinitial":"","lastname":"Stafford","description":"Oceanographer","whotheyare":"Kate Stafford's research examines migratory movements, geographic variation and physical drivers of marine mammals, particularly large whales.","whylisten":"<p>Dr. Kate Stafford has worked in marine habitats all over the world, from the tropics to the poles, and is fortunate enough to have seen (and recorded) blue whales in every ocean in which they occur. Stafford&#39;s current research focuses on the changing acoustic environment of the Arctic and how changes from declining sea ice&nbsp;to increasing industrial human use may be influencing subarctic and Arctic marine mammals.<\/p><p>Stafford is a Principal Oceanographer at the Applied Physics Lab and affiliate Associate Professor in the School of Oceanography at the University of Washington in Seattle. She has degrees in French literature and biology from the University of California at Santa Cruz and wildlife science (MS) and oceanography (PhD) from Oregon State University. Before going to graduate school, she lived as a Fulbright scholar for a year in Paris studying Medieval French literature. Stafford&#39;s research has been featured in <em>Wild Blue: a Natural History of the World&#39;s Largest Animal<\/em> by Dan Bortolotti, the <em>New York Times<\/em>&nbsp;&quot;Scientist at Work&quot; blog, <em>The Planet<\/em> magazine, and in <em>Highlights for Children<\/em> magazine. She has collaborated with artists around the world, providing sounds for multimedia art exhibits.<\/p>","slug":"kate_stafford","published_at":"2017-05-05 15:29:00","updated_at":"2017-05-12 15:01:39"}}