{"speaker":{"id":3939,"title":"","firstname":"Kate","middleinitial":"","lastname":"Raworth","description":"Renegade economist","whotheyare":"Kate Raworth is passionate about making economics fit for the 21st century.","whylisten":"<p>Kate Raworth writes: &quot;I am a renegade economist, dedicated to rewriting economics so that it&#39;s fit for tackling the 21st century&#39;s grand challenge of meeting the needs of all people within the means of the planet. After 20 years of wrestling with policies based on outdated economic theories -- via the villages of Zanzibar to the headquarters of the UN and on the campaigning frontlines of Oxfam -- I realized that if the economic conversations taking place in parliaments, in boardrooms and in the media worldwide are going to change, then the fundamental economic ideas taught in schools and universities have to be transformed, too. <\/p><p>&quot;I wrote <a href=\"https:\/\/www.amazon.com\/Doughnut-Economics-Seven-21st-Century-Economist\/dp\/1603586741?SubscriptionId=AKIAILSHYYTFIVPWUY6Q&amp;tag=duckduckgo-ffab-20&amp;linkCode=xm2&amp;camp=2025&amp;creative=165953&amp;creativeASIN=1603586741\" target=\"_blank\"><em>Doughnut Economics: Seven Ways to Think Like a 21st-Century Economist<\/em><\/a>  to be the book that I wish I could have read when I was a frustrated and disillusioned economics student myself. And silly though it sounds, it all starts with a doughnut (yes, the kind with a hole in the middle), which acts as a compass for 21st-century prosperity, inviting us to rethink what the economy is, and is for, who we are, and what success looks like.&quot; <\/p>","slug":"kate_raworth","published_at":"2018-02-10 23:22:00","updated_at":"2018-05-01 20:55:32"}}