{"speaker":{"id":5983,"title":"","firstname":"Nitish","middleinitial":"","lastname":"Padmanaban","description":"Electrical engineer","whotheyare":"Nitish Padmanaban designs systems that combine optics and computation to help improve visual perception.","whylisten":"<p>Nitish Padmanaban&#39;s work spans virtual reality displays, motion sickness, holography and vision correction. Lately, he has been working on ways of leveraging eye tracking and lens technologies used in virtual reality headsets for correcting presbyopia.<\/p><p>Padmanaban recently finished his PhD at Stanford University in the Stanford Computational Imaging Lab and now works at Zinn Labs to make autofocal presbyopia correction a reality.<\/p>","slug":"nitish_padmanaban","published_at":"2020-05-27 21:04:00","updated_at":"2020-05-27 21:35:04"}}