{"speaker":{"id":6481,"title":"","firstname":"Selina","middleinitial":"","lastname":"Neirok Leem","description":"Youth climate activist","whotheyare":"Born and raised in Majuro, the capital atoll of the Marshall Islands, Selina Neirok Leem was the youngest delegate at the COP21 conference that adopted the Paris Agreement. ","whylisten":"<p>Selina Neirok Leem often calls herself &quot;a small island girl with big dreams.&quot; She credits her grandfather for her deep awareness of the fate of her home --&nbsp;the low-lying Marshall Islands in the Pacific Ocean -- through his stories about how the ice in the North Pole and South Pole were melting and would soon flood the islands.<\/p><p>At the age of 16, Leem moved to Germany to finish high school in the UWC (United World College) Robert Bosch College in Freiburg, where she took on the role of a climate crisis warrior for her country. Representing the Marshall Islands, Leem was the youngest delegate at the COP21 (the 2015 UN Climate Change Conference in Paris). During the closing remarks, then Marshall Islands Foreign Minister Tony deBrum gave her the opportunity to give the final statement on behalf of her country. Leem told the world that the Paris Agreement &quot;should be the turning point in our story -- a turning point for all of us.&quot;<\/p>","slug":"selina_neirok_leem","published_at":"2021-08-10 19:54:00","updated_at":"2022-03-01 18:48:51"}}