{"talk":{"id":11,"name":"Jane Goodall: What separates us from chimpanzees?","description":"Jane Goodall hasn't found the missing link, but she's come closer than nearly anyone else. The primatologist says the only real difference between humans and chimps is our sophisticated language. She urges us to start using it to change the world.","slug":"jane_goodall_what_separates_us_from_chimpanzees","recorded_at":"2003-03-01 00:00:00","published_at":"2007-04-05 00:11:00","updated_at":"2020-10-09 15:41:02","viewed_count":1870224,"emailed_count":895,"event":{"id":6,"name":"TED2003"},"images":[{"image":{"size":"113x85","url":"https:\/\/pe.tedcdn.com\/images\/ted\/c04f9a5ce0d14b18cb5d1519151b3676f1647024_113x85.jpg"}},{"image":{"size":"240x180","url":"https:\/\/pe.tedcdn.com\/images\/ted\/c04f9a5ce0d14b18cb5d1519151b3676f1647024_240x180.jpg"}},{"image":{"size":"615x461","url":"https:\/\/pe.tedcdn.com\/images\/ted\/c04f9a5ce0d14b18cb5d1519151b3676f1647024_615x461.jpg"}},{"image":{"size":"2400x1800","url":"https:\/\/pe.tedcdn.com\/images\/ted\/c04f9a5ce0d14b18cb5d1519151b3676f1647024_2400x1800.jpg"}}],"image_16x9":"https:\/\/pe.tedcdn.com\/images\/ted\/6a8a27b4553f4e39d96139e5199f5bf8a354b410_2880x1620.jpg","media":{"internal":{"64k":{"uri":"https:\/\/download.ted.com\/talks\/JaneGoodall_2003-64k.mp4?apikey=c692baa7dafbf74e4fbde1ac88b44cafc96cfe7a","filesize_bytes":13456177,"mime_type":"video\/mp4"},"180k":{"uri":"https:\/\/download.ted.com\/talks\/JaneGoodall_2003-180k.mp4?apikey=c692baa7dafbf74e4fbde1ac88b44cafc96cfe7a","filesize_bytes":37424375,"mime_type":"video\/mp4"},"320k":{"uri":"https:\/\/download.ted.com\/talks\/JaneGoodall_2003-320k.mp4?apikey=c692baa7dafbf74e4fbde1ac88b44cafc96cfe7a","filesize_bytes":66156343,"mime_type":"video\/mp4"},"450k":{"uri":"https:\/\/download.ted.com\/talks\/JaneGoodall_2003-450k.mp4?apikey=c692baa7dafbf74e4fbde1ac88b44cafc96cfe7a","filesize_bytes":92919594,"mime_type":"video\/mp4"},"600k":{"uri":"https:\/\/download.ted.com\/talks\/JaneGoodall_2003-600k.mp4?apikey=c692baa7dafbf74e4fbde1ac88b44cafc96cfe7a","filesize_bytes":123828546,"mime_type":"video\/mp4"},"950k":{"uri":"https:\/\/download.ted.com\/talks\/JaneGoodall_2003-950k.mp4?apikey=c692baa7dafbf74e4fbde1ac88b44cafc96cfe7a","filesize_bytes":191555490,"mime_type":"video\/mp4"},"1500k":{"uri":"https:\/\/download.ted.com\/talks\/JaneGoodall_2003-1500k.mp4?apikey=c692baa7dafbf74e4fbde1ac88b44cafc96cfe7a","filesize_bytes":300101515,"mime_type":"video\/mp4"},"podcast-light":{"uri":"https:\/\/download.ted.com\/talks\/JaneGoodall_2003-light.mp4?apikey=c692baa7dafbf74e4fbde1ac88b44cafc96cfe7a","filesize_bytes":13588899,"mime_type":"video\/mp4"},"podcast-regular":{"uri":"https:\/\/download.ted.com\/talks\/JaneGoodall_2003.mp4?apikey=c692baa7dafbf74e4fbde1ac88b44cafc96cfe7a","filesize_bytes":93329007,"mime_type":"video\/mp4"},"podcast-high":{"uri":"https:\/\/download.ted.com\/talks\/JaneGoodall_2003-480p.mp4?apikey=c692baa7dafbf74e4fbde1ac88b44cafc96cfe7a","filesize_bytes":191536393,"mime_type":"video\/mp4"},"audio-podcast":{"uri":"https:\/\/download.ted.com\/talks\/JaneGoodall_2003.mp3?apikey=c692baa7dafbf74e4fbde1ac88b44cafc96cfe7a","filesize_bytes":10961988,"mime_type":"audio\/mp3"},"podcast-high-en":{"uri":"https:\/\/download.ted.com\/talks\/JaneGoodall_2003-480p-en.mp4?apikey=c692baa7dafbf74e4fbde1ac88b44cafc96cfe7a","filesize_bytes":191133612,"mime_type":"video\/mp4"},"podcast-low-en":{"uri":"https:\/\/download.ted.com\/talks\/JaneGoodall_2003-low-en.mp4?apikey=c692baa7dafbf74e4fbde1ac88b44cafc96cfe7a","filesize_bytes":37651610,"mime_type":"video\/mp4"}}},"languages":{"ar":{"name":"Arabic"},"bg":{"name":"Bulgarian"},"zh-cn":{"name":"Chinese, Simplified"},"zh-tw":{"name":"Chinese, Traditional"},"hr":{"name":"Croatian"},"cs":{"name":"Czech"},"da":{"name":"Danish"},"nl":{"name":"Dutch"},"en":{"name":"English","native":true},"fi":{"name":"Finnish"},"fr":{"name":"French"},"ka":{"name":"Georgian"},"de":{"name":"German"},"el":{"name":"Greek"},"he":{"name":"Hebrew"},"hu":{"name":"Hungarian"},"it":{"name":"Italian"},"ja":{"name":"Japanese"},"ko":{"name":"Korean"},"fa":{"name":"Persian"},"pl":{"name":"Polish"},"pt":{"name":"Portuguese"},"pt-br":{"name":"Portuguese, Brazilian"},"ro":{"name":"Romanian"},"ru":{"name":"Russian"},"sr":{"name":"Serbian"},"es":{"name":"Spanish"},"sv":{"name":"Swedish"},"th":{"name":"Thai"},"tr":{"name":"Turkish"},"uk":{"name":"Ukrainian"},"vi":{"name":"Vietnamese"}},"tags":[{"tag":"Africa"},{"tag":"animals"},{"tag":"culture"},{"tag":"environment"},{"tag":"global issues"},{"tag":"nature"},{"tag":"primates"},{"tag":"science"}],"themes":[{"theme":{"id":2,"name":"Animals That Amaze"}},{"theme":{"id":3,"name":"Evolution's Genius"}},{"theme":{"id":14,"name":"Inspired by Nature"}},{"theme":{"id":15,"name":"A Greener Future?"}},{"theme":{"id":45,"name":"Africa: The Next Chapter"}},{"theme":{"id":71,"name":"Women Reshaping the World"}}],"speakers":[{"speaker":{"id":12,"name":"Jane Goodall"}}],"ratings":[{"rating":{"id":1,"name":"Beautiful","count":483}},{"rating":{"id":7,"name":"Funny","count":42}},{"rating":{"id":3,"name":"Courageous","count":303}},{"rating":{"id":11,"name":"Longwinded","count":70}},{"rating":{"id":21,"name":"Unconvincing","count":34}},{"rating":{"id":2,"name":"Confusing","count":28}},{"rating":{"id":8,"name":"Informative","count":415}},{"rating":{"id":10,"name":"Inspiring","count":993}},{"rating":{"id":22,"name":"Fascinating","count":457}},{"rating":{"id":9,"name":"Ingenious","count":38}},{"rating":{"id":24,"name":"Persuasive","count":299}},{"rating":{"id":23,"name":"Jaw-dropping","count":108}},{"rating":{"id":26,"name":"Obnoxious","count":27}},{"rating":{"id":25,"name":"OK","count":63}}]}}