{"talk":{"id":13591,"name":"Kasiva Mutua: How I use the drum to tell my story","description":"In this talk-performance hybrid, drummer, percussionist and TED Fellow Kasiva Mutua shares how she's breaking the taboo against female drummers in Kenya -- and her mission to teach the significance and importance of the drum to young boys, women and girls. \"Women can be custodians of culture, too,\" Mutua says.","slug":"kasiva_mutua_how_i_use_the_drum_to_tell_my_story","recorded_at":"2017-08-27 00:00:00","published_at":"2018-04-06 14:32:40","updated_at":"2021-04-09 19:37:25","viewed_count":1157766,"emailed_count":0,"event":{"id":465,"name":"TEDGlobal 2017"},"images":[{"image":{"size":"113x85","url":"https:\/\/pe.tedcdn.com\/images\/ted\/29f844410332a3c973a7f6bdec912c194f00b212_113x85.jpg"}},{"image":{"size":"240x180","url":"https:\/\/pe.tedcdn.com\/images\/ted\/29f844410332a3c973a7f6bdec912c194f00b212_240x180.jpg"}},{"image":{"size":"615x461","url":"https:\/\/pe.tedcdn.com\/images\/ted\/29f844410332a3c973a7f6bdec912c194f00b212_615x461.jpg"}},{"image":{"size":"2400x1800","url":"https:\/\/pe.tedcdn.com\/images\/ted\/29f844410332a3c973a7f6bdec912c194f00b212_2400x1800.jpg"}}],"image_16x9":"https:\/\/pe.tedcdn.com\/images\/ted\/0d49f4b4b126e1b54acd2d1660142cbae89288e6_2880x1620.jpg","media":{"internal":{"64k":{"uri":"https:\/\/download.ted.com\/talks\/KasivaMutua_2017G-64k.mp4?apikey=c692baa7dafbf74e4fbde1ac88b44cafc96cfe7a","filesize_bytes":6253596,"mime_type":"video\/mp4"},"180k":{"uri":"https:\/\/download.ted.com\/talks\/KasivaMutua_2017G-180k.mp4?apikey=c692baa7dafbf74e4fbde1ac88b44cafc96cfe7a","filesize_bytes":17308868,"mime_type":"video\/mp4"},"320k":{"uri":"https:\/\/download.ted.com\/talks\/KasivaMutua_2017G-320k.mp4?apikey=c692baa7dafbf74e4fbde1ac88b44cafc96cfe7a","filesize_bytes":30694784,"mime_type":"video\/mp4"},"450k":{"uri":"https:\/\/download.ted.com\/talks\/KasivaMutua_2017G-450k.mp4?apikey=c692baa7dafbf74e4fbde1ac88b44cafc96cfe7a","filesize_bytes":43230469,"mime_type":"video\/mp4"},"600k":{"uri":"https:\/\/download.ted.com\/talks\/KasivaMutua_2017G-600k.mp4?apikey=c692baa7dafbf74e4fbde1ac88b44cafc96cfe7a","filesize_bytes":57840990,"mime_type":"video\/mp4"},"950k":{"uri":"https:\/\/download.ted.com\/talks\/KasivaMutua_2017G-950k.mp4?apikey=c692baa7dafbf74e4fbde1ac88b44cafc96cfe7a","filesize_bytes":90760836,"mime_type":"video\/mp4"},"1500k":{"uri":"https:\/\/download.ted.com\/talks\/KasivaMutua_2017G-1500k.mp4?apikey=c692baa7dafbf74e4fbde1ac88b44cafc96cfe7a","filesize_bytes":140414704,"mime_type":"video\/mp4"},"podcast-light":{"uri":"https:\/\/download.ted.com\/talks\/KasivaMutua_2017G-light.mp4?apikey=c692baa7dafbf74e4fbde1ac88b44cafc96cfe7a","filesize_bytes":6518813,"mime_type":"video\/mp4"},"podcast-regular":{"uri":"https:\/\/download.ted.com\/talks\/KasivaMutua_2017G.mp4?apikey=c692baa7dafbf74e4fbde1ac88b44cafc96cfe7a","filesize_bytes":43586620,"mime_type":"video\/mp4"},"podcast-high":{"uri":"https:\/\/download.ted.com\/talks\/KasivaMutua_2017G-480p.mp4?apikey=c692baa7dafbf74e4fbde1ac88b44cafc96cfe7a","filesize_bytes":91321921,"mime_type":"video\/mp4"},"audio-podcast":{"uri":"https:\/\/download.ted.com\/talks\/KasivaMutua_2017G.mp3?apikey=c692baa7dafbf74e4fbde1ac88b44cafc96cfe7a","filesize_bytes":7590713,"mime_type":"audio\/mp3"},"podcast-low-en":{"uri":"https:\/\/download.ted.com\/talks\/KasivaMutua_2017G-low-en.mp4?apikey=c692baa7dafbf74e4fbde1ac88b44cafc96cfe7a","filesize_bytes":17581326,"mime_type":"video\/mp4"},"podcast-high-en":{"uri":"https:\/\/download.ted.com\/talks\/KasivaMutua_2017G-480p-en.mp4?apikey=c692baa7dafbf74e4fbde1ac88b44cafc96cfe7a","filesize_bytes":91319462,"mime_type":"video\/mp4"}}},"languages":{"ar":{"name":"Arabic"},"zh-cn":{"name":"Chinese, Simplified"},"zh-tw":{"name":"Chinese, Traditional"},"en":{"name":"English","native":true},"fr":{"name":"French"},"de":{"name":"German"},"hu":{"name":"Hungarian"},"ja":{"name":"Japanese"},"ko":{"name":"Korean"},"fa":{"name":"Persian"},"pt":{"name":"Portuguese"},"pt-br":{"name":"Portuguese, Brazilian"},"ru":{"name":"Russian"},"sr":{"name":"Serbian"},"es":{"name":"Spanish"},"th":{"name":"Thai"},"tr":{"name":"Turkish"},"vi":{"name":"Vietnamese"}},"tags":[{"tag":"Africa"},{"tag":"TED Fellows"},{"tag":"art"},{"tag":"entertainment"},{"tag":"music"},{"tag":"performance"}],"themes":[],"speakers":[{"speaker":{"id":3574,"name":"Kasiva Mutua"}}],"ratings":[{"rating":{"id":21,"name":"Unconvincing","count":12}},{"rating":{"id":1,"name":"Beautiful","count":82}},{"rating":{"id":3,"name":"Courageous","count":39}},{"rating":{"id":10,"name":"Inspiring","count":107}},{"rating":{"id":11,"name":"Longwinded","count":9}},{"rating":{"id":8,"name":"Informative","count":25}},{"rating":{"id":7,"name":"Funny","count":14}},{"rating":{"id":9,"name":"Ingenious","count":4}},{"rating":{"id":22,"name":"Fascinating","count":44}},{"rating":{"id":24,"name":"Persuasive","count":13}},{"rating":{"id":25,"name":"OK","count":20}},{"rating":{"id":23,"name":"Jaw-dropping","count":13}},{"rating":{"id":26,"name":"Obnoxious","count":3}},{"rating":{"id":2,"name":"Confusing","count":4}}]}}