{"talk":{"id":186,"name":"Rokia Traore: \"M'Bifo\"","description":"Rokia Traore sings the moving \"M'Bifo,\" accompanied on the n'goni, a lute-like Malian stringed instrument with a soulful timbre. A quietly mesmerizing performance.","slug":"rokia_traore_m_bifo","recorded_at":"2007-06-06 00:00:00","published_at":"2008-03-27 01:18:00","updated_at":"2021-04-09 19:38:20","viewed_count":308221,"emailed_count":474,"event":{"id":10,"name":"TEDGlobal 2007"},"images":[{"image":{"size":"113x85","url":"https:\/\/pe.tedcdn.com\/images\/ted\/c77780f0516e0850d0c241e242012f0540aaed2b_113x85.jpg"}},{"image":{"size":"240x180","url":"https:\/\/pe.tedcdn.com\/images\/ted\/c77780f0516e0850d0c241e242012f0540aaed2b_240x180.jpg"}},{"image":{"size":"615x461","url":"https:\/\/pe.tedcdn.com\/images\/ted\/c77780f0516e0850d0c241e242012f0540aaed2b_615x461.jpg"}},{"image":{"size":"2400x1800","url":"https:\/\/pe.tedcdn.com\/images\/ted\/c77780f0516e0850d0c241e242012f0540aaed2b_2400x1800.jpg"}}],"image_16x9":"https:\/\/pe.tedcdn.com\/images\/ted\/4495674cbeedb2cae157ed1f7f85e4b888317d9a_2880x1620.jpg","media":{"internal":{"64k":{"uri":"https:\/\/download.ted.com\/talks\/RokiaTraore_MBifo_2007G-64k.mp4?apikey=c692baa7dafbf74e4fbde1ac88b44cafc96cfe7a","filesize_bytes":3463708,"mime_type":"video\/mp4"},"180k":{"uri":"https:\/\/download.ted.com\/talks\/RokiaTraore_MBifo_2007G-180k.mp4?apikey=c692baa7dafbf74e4fbde1ac88b44cafc96cfe7a","filesize_bytes":9481121,"mime_type":"video\/mp4"},"320k":{"uri":"https:\/\/download.ted.com\/talks\/RokiaTraore_MBifo_2007G-320k.mp4?apikey=c692baa7dafbf74e4fbde1ac88b44cafc96cfe7a","filesize_bytes":17032645,"mime_type":"video\/mp4"},"450k":{"uri":"https:\/\/download.ted.com\/talks\/RokiaTraore_MBifo_2007G-450k.mp4?apikey=c692baa7dafbf74e4fbde1ac88b44cafc96cfe7a","filesize_bytes":23923967,"mime_type":"video\/mp4"},"600k":{"uri":"https:\/\/download.ted.com\/talks\/RokiaTraore_MBifo_2007G-600k.mp4?apikey=c692baa7dafbf74e4fbde1ac88b44cafc96cfe7a","filesize_bytes":32010434,"mime_type":"video\/mp4"},"950k":{"uri":"https:\/\/download.ted.com\/talks\/RokiaTraore_MBifo_2007G-950k.mp4?apikey=c692baa7dafbf74e4fbde1ac88b44cafc96cfe7a","filesize_bytes":48868107,"mime_type":"video\/mp4"},"1500k":{"uri":"https:\/\/download.ted.com\/talks\/RokiaTraore_MBifo_2007G-1500k.mp4?apikey=c692baa7dafbf74e4fbde1ac88b44cafc96cfe7a","filesize_bytes":76439175,"mime_type":"video\/mp4"}}},"tags":[{"tag":"Africa"},{"tag":"entertainment"},{"tag":"music"},{"tag":"performance"}],"themes":[{"theme":{"id":1,"name":"The Creative Spark"}},{"theme":{"id":9,"name":"Spectacular Performance"}},{"theme":{"id":36,"name":"Live Music"}},{"theme":{"id":45,"name":"Africa: The Next Chapter"}}],"speakers":[{"speaker":{"id":166,"name":"Rokia Traore"}}],"ratings":[{"rating":{"id":23,"name":"Jaw-dropping","count":53}},{"rating":{"id":22,"name":"Fascinating","count":107}},{"rating":{"id":1,"name":"Beautiful","count":534}},{"rating":{"id":25,"name":"OK","count":71}},{"rating":{"id":10,"name":"Inspiring","count":118}},{"rating":{"id":9,"name":"Ingenious","count":8}},{"rating":{"id":24,"name":"Persuasive","count":14}},{"rating":{"id":3,"name":"Courageous","count":20}},{"rating":{"id":21,"name":"Unconvincing","count":6}},{"rating":{"id":2,"name":"Confusing","count":14}},{"rating":{"id":11,"name":"Longwinded","count":3}},{"rating":{"id":26,"name":"Obnoxious","count":5}},{"rating":{"id":8,"name":"Informative","count":1}}]}}