{"talk":{"id":1989,"name":"Sarah Jones: What does the future hold? 11 characters offer quirky answers","description":"Sarah Jones changes personas with the simplest of wardrobe swaps. In a laugh-out-loud improvisation, she invites 11 \"friends\" from the future on stage\u2014from a fast-talking Latina to an outspoken police officer\u2014to ask them questions supplied by the TED2014 audience.","slug":"sarah_jones_what_does_the_future_hold_11_characters_offer_quirky_answers","recorded_at":"2014-03-21 00:00:00","published_at":"2014-05-02 14:56:20","updated_at":"2020-09-28 21:46:06","viewed_count":1655314,"emailed_count":0,"event":{"id":256,"name":"TED2014"},"images":[{"image":{"size":"113x85","url":"https:\/\/pe.tedcdn.com\/images\/ted\/974f4028e20390247c51cca4cbe5fbdbc3eab9e0_113x85.jpg"}},{"image":{"size":"240x180","url":"https:\/\/pe.tedcdn.com\/images\/ted\/974f4028e20390247c51cca4cbe5fbdbc3eab9e0_240x180.jpg"}},{"image":{"size":"615x461","url":"https:\/\/pe.tedcdn.com\/images\/ted\/974f4028e20390247c51cca4cbe5fbdbc3eab9e0_615x461.jpg"}},{"image":{"size":"1600x1200","url":"https:\/\/pe.tedcdn.com\/images\/ted\/974f4028e20390247c51cca4cbe5fbdbc3eab9e0_1600x1200.jpg"}}],"image_16x9":false,"media":{"internal":{"64k":{"uri":"https:\/\/download.ted.com\/talks\/SarahJones_2014-64k.mp4?apikey=c692baa7dafbf74e4fbde1ac88b44cafc96cfe7a","filesize_bytes":9136071,"mime_type":"video\/mp4"},"180k":{"uri":"https:\/\/download.ted.com\/talks\/SarahJones_2014-180k.mp4?apikey=c692baa7dafbf74e4fbde1ac88b44cafc96cfe7a","filesize_bytes":25361914,"mime_type":"video\/mp4"},"320k":{"uri":"https:\/\/download.ted.com\/talks\/SarahJones_2014-320k.mp4?apikey=c692baa7dafbf74e4fbde1ac88b44cafc96cfe7a","filesize_bytes":44895528,"mime_type":"video\/mp4"},"450k":{"uri":"https:\/\/download.ted.com\/talks\/SarahJones_2014-450k.mp4?apikey=c692baa7dafbf74e4fbde1ac88b44cafc96cfe7a","filesize_bytes":63176270,"mime_type":"video\/mp4"},"600k":{"uri":"https:\/\/download.ted.com\/talks\/SarahJones_2014-600k.mp4?apikey=c692baa7dafbf74e4fbde1ac88b44cafc96cfe7a","filesize_bytes":84421661,"mime_type":"video\/mp4"},"950k":{"uri":"https:\/\/download.ted.com\/talks\/SarahJones_2014-950k.mp4?apikey=c692baa7dafbf74e4fbde1ac88b44cafc96cfe7a","filesize_bytes":132637426,"mime_type":"video\/mp4"},"1500k":{"uri":"https:\/\/download.ted.com\/talks\/SarahJones_2014-1500k.mp4?apikey=c692baa7dafbf74e4fbde1ac88b44cafc96cfe7a","filesize_bytes":205889014,"mime_type":"video\/mp4"},"podcast-light":{"uri":"https:\/\/download.ted.com\/talks\/SarahJones_2014-light.mp4?apikey=c692baa7dafbf74e4fbde1ac88b44cafc96cfe7a","filesize_bytes":9269505,"mime_type":"video\/mp4"},"podcast-regular":{"uri":"https:\/\/download.ted.com\/talks\/SarahJones_2014.mp4?apikey=c692baa7dafbf74e4fbde1ac88b44cafc96cfe7a","filesize_bytes":63291399,"mime_type":"video\/mp4"},"podcast-high":{"uri":"https:\/\/download.ted.com\/talks\/SarahJones_2014-480p.mp4?apikey=c692baa7dafbf74e4fbde1ac88b44cafc96cfe7a","filesize_bytes":132629376,"mime_type":"video\/mp4"},"audio-podcast":{"uri":"https:\/\/download.ted.com\/talks\/SarahJones_2014.mp3?apikey=c692baa7dafbf74e4fbde1ac88b44cafc96cfe7a","filesize_bytes":11406150,"mime_type":"audio\/mp3"},"podcast-low-en":{"uri":"https:\/\/download.ted.com\/talks\/SarahJones_2014-low-en.mp4?apikey=c692baa7dafbf74e4fbde1ac88b44cafc96cfe7a","filesize_bytes":25614976,"mime_type":"video\/mp4"},"podcast-high-en":{"uri":"https:\/\/download.ted.com\/talks\/SarahJones_2014-480p-en.mp4?apikey=c692baa7dafbf74e4fbde1ac88b44cafc96cfe7a","filesize_bytes":132644350,"mime_type":"video\/mp4"}}},"languages":{"sq":{"name":"Albanian"},"ar":{"name":"Arabic"},"zh-cn":{"name":"Chinese, Simplified"},"zh-tw":{"name":"Chinese, Traditional"},"en":{"name":"English","native":true},"fr":{"name":"French"},"el":{"name":"Greek"},"he":{"name":"Hebrew"},"it":{"name":"Italian"},"ja":{"name":"Japanese"},"ko":{"name":"Korean"},"fa":{"name":"Persian"},"pt":{"name":"Portuguese"},"pt-br":{"name":"Portuguese, Brazilian"},"ro":{"name":"Romanian"},"ru":{"name":"Russian"},"sr":{"name":"Serbian"},"sl":{"name":"Slovenian"},"es":{"name":"Spanish"},"th":{"name":"Thai"},"vi":{"name":"Vietnamese"}},"tags":[{"tag":"future"},{"tag":"humor"},{"tag":"performance"},{"tag":"theater"}],"themes":[{"theme":{"id":9,"name":"Spectacular Performance"}}],"speakers":[{"speaker":{"id":370,"name":"Sarah Jones"}}],"ratings":[{"rating":{"id":7,"name":"Funny","count":496}},{"rating":{"id":1,"name":"Beautiful","count":141}},{"rating":{"id":11,"name":"Longwinded","count":73}},{"rating":{"id":25,"name":"OK","count":121}},{"rating":{"id":10,"name":"Inspiring","count":139}},{"rating":{"id":22,"name":"Fascinating","count":109}},{"rating":{"id":8,"name":"Informative","count":32}},{"rating":{"id":9,"name":"Ingenious","count":148}},{"rating":{"id":2,"name":"Confusing","count":43}},{"rating":{"id":21,"name":"Unconvincing","count":38}},{"rating":{"id":3,"name":"Courageous","count":83}},{"rating":{"id":23,"name":"Jaw-dropping","count":54}},{"rating":{"id":26,"name":"Obnoxious","count":60}},{"rating":{"id":24,"name":"Persuasive","count":10}}]}}