{"talk":{"id":2834,"name":"Manoush Zomorodi: How boredom can lead to your most brilliant ideas","description":"Do you sometimes have your most creative ideas while folding laundry, washing dishes or doing nothing in particular? It's because when your body goes on autopilot, your brain gets busy forming new neural connections that connect ideas and solve problems. Learn to love being bored as Manoush Zomorodi explains the connection between spacing out and creativity.","slug":"manoush_zomorodi_how_boredom_can_lead_to_your_most_brilliant_ideas","recorded_at":"2017-04-24 00:00:00","published_at":"2017-08-15 15:00:23","updated_at":"2021-04-13 21:31:32","viewed_count":3077800,"emailed_count":0,"event":{"id":455,"name":"TED2017"},"images":[{"image":{"size":"113x85","url":"https:\/\/pe.tedcdn.com\/images\/ted\/9e5e321e1c15c3597d0d23fa53b538dfc2b34bd0_113x85.jpg"}},{"image":{"size":"240x180","url":"https:\/\/pe.tedcdn.com\/images\/ted\/9e5e321e1c15c3597d0d23fa53b538dfc2b34bd0_240x180.jpg"}},{"image":{"size":"615x461","url":"https:\/\/pe.tedcdn.com\/images\/ted\/9e5e321e1c15c3597d0d23fa53b538dfc2b34bd0_615x461.jpg"}},{"image":{"size":"2400x1800","url":"https:\/\/pe.tedcdn.com\/images\/ted\/9e5e321e1c15c3597d0d23fa53b538dfc2b34bd0_2400x1800.jpg"}}],"image_16x9":"https:\/\/pe.tedcdn.com\/images\/ted\/726ed8a7b257e0721dc095c4d21489bae403b93f_2880x1620.jpg","media":{"internal":{"64k":{"uri":"https:\/\/download.ted.com\/talks\/ManoushZomorodi_2017-64k.mp4?apikey=c692baa7dafbf74e4fbde1ac88b44cafc96cfe7a","filesize_bytes":8025592,"mime_type":"video\/mp4"},"180k":{"uri":"https:\/\/download.ted.com\/talks\/ManoushZomorodi_2017-180k.mp4?apikey=c692baa7dafbf74e4fbde1ac88b44cafc96cfe7a","filesize_bytes":22232737,"mime_type":"video\/mp4"},"320k":{"uri":"https:\/\/download.ted.com\/talks\/ManoushZomorodi_2017-320k.mp4?apikey=c692baa7dafbf74e4fbde1ac88b44cafc96cfe7a","filesize_bytes":39368904,"mime_type":"video\/mp4"},"450k":{"uri":"https:\/\/download.ted.com\/talks\/ManoushZomorodi_2017-450k.mp4?apikey=c692baa7dafbf74e4fbde1ac88b44cafc96cfe7a","filesize_bytes":55425587,"mime_type":"video\/mp4"},"600k":{"uri":"https:\/\/download.ted.com\/talks\/ManoushZomorodi_2017-600k.mp4?apikey=c692baa7dafbf74e4fbde1ac88b44cafc96cfe7a","filesize_bytes":74093717,"mime_type":"video\/mp4"},"950k":{"uri":"https:\/\/download.ted.com\/talks\/ManoushZomorodi_2017-950k.mp4?apikey=c692baa7dafbf74e4fbde1ac88b44cafc96cfe7a","filesize_bytes":116228065,"mime_type":"video\/mp4"},"1500k":{"uri":"https:\/\/download.ted.com\/talks\/ManoushZomorodi_2017-1500k.mp4?apikey=c692baa7dafbf74e4fbde1ac88b44cafc96cfe7a","filesize_bytes":180264068,"mime_type":"video\/mp4"},"podcast-light":{"uri":"https:\/\/download.ted.com\/talks\/ManoushZomorodi_2017-light.mp4?apikey=c692baa7dafbf74e4fbde1ac88b44cafc96cfe7a","filesize_bytes":8239869,"mime_type":"video\/mp4"},"podcast-regular":{"uri":"https:\/\/download.ted.com\/talks\/ManoushZomorodi_2017.mp4?apikey=c692baa7dafbf74e4fbde1ac88b44cafc96cfe7a","filesize_bytes":55591445,"mime_type":"video\/mp4"},"podcast-high":{"uri":"https:\/\/download.ted.com\/talks\/ManoushZomorodi_2017-480p.mp4?apikey=c692baa7dafbf74e4fbde1ac88b44cafc96cfe7a","filesize_bytes":116364502,"mime_type":"video\/mp4"},"audio-podcast":{"uri":"https:\/\/download.ted.com\/talks\/ManoushZomorodi_2017.mp3?apikey=c692baa7dafbf74e4fbde1ac88b44cafc96cfe7a","filesize_bytes":10068686,"mime_type":"audio\/mp3"},"podcast-low-en":{"uri":"https:\/\/download.ted.com\/talks\/ManoushZomorodi_2017-low-en.mp4?apikey=c692baa7dafbf74e4fbde1ac88b44cafc96cfe7a","filesize_bytes":22484082,"mime_type":"video\/mp4"},"podcast-high-en":{"uri":"https:\/\/download.ted.com\/talks\/ManoushZomorodi_2017-480p-en.mp4?apikey=c692baa7dafbf74e4fbde1ac88b44cafc96cfe7a","filesize_bytes":116369422,"mime_type":"video\/mp4"}}},"languages":{"ar":{"name":"Arabic"},"zh-cn":{"name":"Chinese, Simplified"},"zh-tw":{"name":"Chinese, Traditional"},"nl":{"name":"Dutch"},"en":{"name":"English","native":true},"fr":{"name":"French"},"de":{"name":"German"},"el":{"name":"Greek"},"he":{"name":"Hebrew"},"hu":{"name":"Hungarian"},"ja":{"name":"Japanese"},"ko":{"name":"Korean"},"fa":{"name":"Persian"},"pt-br":{"name":"Portuguese, Brazilian"},"ro":{"name":"Romanian"},"ru":{"name":"Russian"},"sr":{"name":"Serbian"},"es":{"name":"Spanish"},"th":{"name":"Thai"},"tr":{"name":"Turkish"},"uk":{"name":"Ukrainian"},"vi":{"name":"Vietnamese"}},"tags":[{"tag":"Addiction"},{"tag":"brain"},{"tag":"cognitive science"},{"tag":"communication"},{"tag":"creativity"},{"tag":"entertainment"},{"tag":"personal growth"},{"tag":"social media"}],"themes":[],"speakers":[{"speaker":{"id":3400,"name":"Manoush Zomorodi"}}],"ratings":[{"rating":{"id":1,"name":"Beautiful","count":161}},{"rating":{"id":8,"name":"Informative","count":486}},{"rating":{"id":10,"name":"Inspiring","count":658}},{"rating":{"id":9,"name":"Ingenious","count":108}},{"rating":{"id":22,"name":"Fascinating","count":300}},{"rating":{"id":11,"name":"Longwinded","count":17}},{"rating":{"id":21,"name":"Unconvincing","count":12}},{"rating":{"id":25,"name":"OK","count":57}},{"rating":{"id":24,"name":"Persuasive","count":271}},{"rating":{"id":23,"name":"Jaw-dropping","count":55}},{"rating":{"id":7,"name":"Funny","count":162}},{"rating":{"id":3,"name":"Courageous","count":68}},{"rating":{"id":26,"name":"Obnoxious","count":13}},{"rating":{"id":2,"name":"Confusing","count":6}}]}}