{"talk":{"id":35764,"name":"Majd Mashharawi: How I'm making bricks out of ashes and rubble in Gaza","description":"Majd Mashharawi was walking through her war-torn neighborhood in Gaza when an idea flashed in her mind: What if she could take the rubble and transform it into building materials? See how she designed a brick made out of ashes that's helping people rebuild their homes -- and learn about her new project: bringing solar-powered energy to families living in darkness.","slug":"majd_mashharawi_how_i_m_making_bricks_out_of_ashes_and_rubble_in_gaza","recorded_at":"2018-11-28 00:00:00","published_at":"2019-03-04 15:52:58","updated_at":"2021-04-09 19:33:13","viewed_count":799137,"emailed_count":0,"event":{"id":574,"name":"TEDWomen 2018"},"images":[{"image":{"size":"113x85","url":"https:\/\/pe.tedcdn.com\/images\/ted\/535435a4cce90e24d92c00ef557ff29d3efc20f8_113x85.jpg"}},{"image":{"size":"240x180","url":"https:\/\/pe.tedcdn.com\/images\/ted\/535435a4cce90e24d92c00ef557ff29d3efc20f8_240x180.jpg"}},{"image":{"size":"615x461","url":"https:\/\/pe.tedcdn.com\/images\/ted\/535435a4cce90e24d92c00ef557ff29d3efc20f8_615x461.jpg"}},{"image":{"size":"2400x1800","url":"https:\/\/pe.tedcdn.com\/images\/ted\/535435a4cce90e24d92c00ef557ff29d3efc20f8_2400x1800.jpg"}}],"image_16x9":"https:\/\/pe.tedcdn.com\/images\/ted\/29da39537f3c94e0c8284cff169b1fe905eaba15_2880x1620.jpg","media":{"internal":{"64k":{"uri":"https:\/\/download.ted.com\/talks\/MajdMashharawi_2018W-64k.mp4?apikey=c692baa7dafbf74e4fbde1ac88b44cafc96cfe7a","filesize_bytes":5319063,"mime_type":"video\/mp4"},"180k":{"uri":"https:\/\/download.ted.com\/talks\/MajdMashharawi_2018W-180k.mp4?apikey=c692baa7dafbf74e4fbde1ac88b44cafc96cfe7a","filesize_bytes":14731374,"mime_type":"video\/mp4"},"320k":{"uri":"https:\/\/download.ted.com\/talks\/MajdMashharawi_2018W-320k.mp4?apikey=c692baa7dafbf74e4fbde1ac88b44cafc96cfe7a","filesize_bytes":26095534,"mime_type":"video\/mp4"},"450k":{"uri":"https:\/\/download.ted.com\/talks\/MajdMashharawi_2018W-450k.mp4?apikey=c692baa7dafbf74e4fbde1ac88b44cafc96cfe7a","filesize_bytes":36795793,"mime_type":"video\/mp4"},"600k":{"uri":"https:\/\/download.ted.com\/talks\/MajdMashharawi_2018W-600k.mp4?apikey=c692baa7dafbf74e4fbde1ac88b44cafc96cfe7a","filesize_bytes":49292407,"mime_type":"video\/mp4"},"950k":{"uri":"https:\/\/download.ted.com\/talks\/MajdMashharawi_2018W-950k.mp4?apikey=c692baa7dafbf74e4fbde1ac88b44cafc96cfe7a","filesize_bytes":77328698,"mime_type":"video\/mp4"},"1500k":{"uri":"https:\/\/download.ted.com\/talks\/MajdMashharawi_2018W-1500k.mp4?apikey=c692baa7dafbf74e4fbde1ac88b44cafc96cfe7a","filesize_bytes":119473096,"mime_type":"video\/mp4"},"podcast-light":{"uri":"https:\/\/download.ted.com\/talks\/MajdMashharawi_2018W-light.mp4?apikey=c692baa7dafbf74e4fbde1ac88b44cafc96cfe7a","filesize_bytes":5533289,"mime_type":"video\/mp4"},"podcast-regular":{"uri":"https:\/\/download.ted.com\/talks\/MajdMashharawi_2018W.mp4?apikey=c692baa7dafbf74e4fbde1ac88b44cafc96cfe7a","filesize_bytes":36961567,"mime_type":"video\/mp4"},"podcast-high":{"uri":"https:\/\/download.ted.com\/talks\/MajdMashharawi_2018W-480p.mp4?apikey=c692baa7dafbf74e4fbde1ac88b44cafc96cfe7a","filesize_bytes":77464952,"mime_type":"video\/mp4"},"audio-podcast":{"uri":"https:\/\/download.ted.com\/talks\/MajdMashharawi_2018W.mp3?apikey=c692baa7dafbf74e4fbde1ac88b44cafc96cfe7a","filesize_bytes":6271270,"mime_type":"audio\/mp3"},"podcast-low-en":{"uri":"https:\/\/download.ted.com\/talks\/MajdMashharawi_2018W-low-en.mp4?apikey=c692baa7dafbf74e4fbde1ac88b44cafc96cfe7a","filesize_bytes":14987798,"mime_type":"video\/mp4"},"podcast-high-en":{"uri":"https:\/\/download.ted.com\/talks\/MajdMashharawi_2018W-480p-en.mp4?apikey=c692baa7dafbf74e4fbde1ac88b44cafc96cfe7a","filesize_bytes":77459583,"mime_type":"video\/mp4"}}},"languages":{"ar":{"name":"Arabic"},"zh-cn":{"name":"Chinese, Simplified"},"zh-tw":{"name":"Chinese, Traditional"},"cs":{"name":"Czech"},"en":{"name":"English","native":true},"fr":{"name":"French"},"he":{"name":"Hebrew"},"hu":{"name":"Hungarian"},"it":{"name":"Italian"},"ja":{"name":"Japanese"},"ko":{"name":"Korean"},"fa":{"name":"Persian"},"pt":{"name":"Portuguese"},"pt-br":{"name":"Portuguese, Brazilian"},"ro":{"name":"Romanian"},"ru":{"name":"Russian"},"es":{"name":"Spanish"},"tr":{"name":"Turkish"}},"tags":[{"tag":"architecture"},{"tag":"design"},{"tag":"energy"},{"tag":"engineering"},{"tag":"invention"},{"tag":"solar energy"},{"tag":"sustainability"},{"tag":"technology"},{"tag":"war"}],"themes":[],"speakers":[{"speaker":{"id":4901,"name":"Majd Mashharawi"}}],"ratings":[]}}