{"talk":{"id":68078,"name":"Cedric Habiyaremye: How quinoa can help combat hunger and malnutrition","description":"On a mission to create a hunger-free world, agricultural entrepreneur Cedric Habiyaremye makes the case for cultivating quinoa -- and other versatile, nutrient-rich grains -- in places experiencing malnutrition, like his native Rwanda. He shares a model to help smallholder farmers across Africa diversify their fields with nutritious and indigenous crops, taking a step towards ensuring healthy foods are available and affordable for all.","slug":"cedric_habiyaremye_how_quinoa_can_help_combat_hunger_and_malnutrition","recorded_at":"2020-05-18 00:00:00","published_at":"2020-11-19 15:48:17","updated_at":"2021-10-22 20:57:15","viewed_count":0,"emailed_count":0,"event":{"id":644,"name":"TED2020 "},"images":[{"image":{"size":"113x85","url":"https:\/\/pe.tedcdn.com\/images\/ted\/9acd4391a1aaa102497c0b57344769cabbc310a9_113x85.jpg"}},{"image":{"size":"240x180","url":"https:\/\/pe.tedcdn.com\/images\/ted\/9acd4391a1aaa102497c0b57344769cabbc310a9_240x180.jpg"}},{"image":{"size":"615x461","url":"https:\/\/pe.tedcdn.com\/images\/ted\/9acd4391a1aaa102497c0b57344769cabbc310a9_615x461.jpg"}},{"image":{"size":"2400x1800","url":"https:\/\/pe.tedcdn.com\/images\/ted\/9acd4391a1aaa102497c0b57344769cabbc310a9_2400x1800.jpg"}}],"image_16x9":"https:\/\/pe.tedcdn.com\/images\/ted\/8f46b5e57d67a32bbedd15e6b0909ae3c6f0d4cd_2880x1620.jpg","media":{"internal":{"64k":{"uri":"https:\/\/download.ted.com\/talks\/CedricHabiyaremye_2020-64k.mp4?apikey=c692baa7dafbf74e4fbde1ac88b44cafc96cfe7a","filesize_bytes":3336354,"mime_type":"video\/mp4"},"180k":{"uri":"https:\/\/download.ted.com\/talks\/CedricHabiyaremye_2020-180k.mp4?apikey=c692baa7dafbf74e4fbde1ac88b44cafc96cfe7a","filesize_bytes":9181021,"mime_type":"video\/mp4"},"320k":{"uri":"https:\/\/download.ted.com\/talks\/CedricHabiyaremye_2020-320k.mp4?apikey=c692baa7dafbf74e4fbde1ac88b44cafc96cfe7a","filesize_bytes":16285719,"mime_type":"video\/mp4"},"450k":{"uri":"https:\/\/download.ted.com\/talks\/CedricHabiyaremye_2020-450k.mp4?apikey=c692baa7dafbf74e4fbde1ac88b44cafc96cfe7a","filesize_bytes":23041329,"mime_type":"video\/mp4"},"600k":{"uri":"https:\/\/download.ted.com\/talks\/CedricHabiyaremye_2020-600k.mp4?apikey=c692baa7dafbf74e4fbde1ac88b44cafc96cfe7a","filesize_bytes":30966481,"mime_type":"video\/mp4"},"950k":{"uri":"https:\/\/download.ted.com\/talks\/CedricHabiyaremye_2020-950k.mp4?apikey=c692baa7dafbf74e4fbde1ac88b44cafc96cfe7a","filesize_bytes":47295125,"mime_type":"video\/mp4"},"1500k":{"uri":"https:\/\/download.ted.com\/talks\/CedricHabiyaremye_2020-1500k.mp4?apikey=c692baa7dafbf74e4fbde1ac88b44cafc96cfe7a","filesize_bytes":72752342,"mime_type":"video\/mp4"},"podcast-light":{"uri":"https:\/\/download.ted.com\/talks\/CedricHabiyaremye_2020-light.mp4?apikey=c692baa7dafbf74e4fbde1ac88b44cafc96cfe7a","filesize_bytes":3550432,"mime_type":"video\/mp4"},"podcast-regular":{"uri":"https:\/\/download.ted.com\/talks\/CedricHabiyaremye_2020.mp4?apikey=c692baa7dafbf74e4fbde1ac88b44cafc96cfe7a","filesize_bytes":23207359,"mime_type":"video\/mp4"},"podcast-high":{"uri":"https:\/\/download.ted.com\/talks\/CedricHabiyaremye_2020-480p.mp4?apikey=c692baa7dafbf74e4fbde1ac88b44cafc96cfe7a","filesize_bytes":47449585,"mime_type":"video\/mp4"},"audio-podcast":{"uri":"https:\/\/download.ted.com\/talks\/CedricHabiyaremye_2020.mp3?apikey=c692baa7dafbf74e4fbde1ac88b44cafc96cfe7a","filesize_bytes":4284655,"mime_type":"audio\/mp3"},"podcast-low-en":{"uri":"https:\/\/download.ted.com\/talks\/CedricHabiyaremye_2020-low-en.mp4?apikey=c692baa7dafbf74e4fbde1ac88b44cafc96cfe7a","filesize_bytes":9445248,"mime_type":"video\/mp4"},"podcast-high-en":{"uri":"https:\/\/download.ted.com\/talks\/CedricHabiyaremye_2020-480p-en.mp4?apikey=c692baa7dafbf74e4fbde1ac88b44cafc96cfe7a","filesize_bytes":47457396,"mime_type":"video\/mp4"}}},"languages":{"ar":{"name":"Arabic"},"zh-cn":{"name":"Chinese, Simplified"},"zh-tw":{"name":"Chinese, Traditional"},"en":{"name":"English","native":true},"fr":{"name":"French"},"de":{"name":"German"},"hu":{"name":"Hungarian"},"id":{"name":"Indonesian"},"ko":{"name":"Korean"},"ckb":{"name":"Kurdish (Central)"},"pt":{"name":"Portuguese"},"pt-br":{"name":"Portuguese, Brazilian"},"ro":{"name":"Romanian"},"sr":{"name":"Serbian"},"es":{"name":"Spanish"},"tr":{"name":"Turkish"}},"tags":[{"tag":"agriculture"},{"tag":"farming"},{"tag":"food"},{"tag":"global issues"},{"tag":"poverty"},{"tag":"society"}],"themes":[],"speakers":[{"speaker":{"id":5825,"name":"Cedric Habiyaremye"}}],"ratings":[]}}